BCEmbedding/__init__.py
BCEmbedding/evaluation/__init__.py
BCEmbedding/evaluation/c_mteb/Reranking.py
BCEmbedding/evaluation/c_mteb/Retrieval.py
BCEmbedding/evaluation/c_mteb/__init__.py
BCEmbedding/evaluation/c_mteb/yd_dres_model.py
BCEmbedding/models/__init__.py
BCEmbedding/models/embedding.py
BCEmbedding/models/reranker.py
BCEmbedding/models/utils.py
BCEmbedding/tools/__init__.py
BCEmbedding/tools/langchain/__init__.py
BCEmbedding/tools/langchain/bce_rerank.py
BCEmbedding/tools/llama_index/__init__.py
BCEmbedding/tools/llama_index/bce_rerank.py
BCEmbedding/utils/__init__.py
BCEmbedding/utils/logger.py
BCEmbedding/utils/query_instructions.py
BCEmbedding-0.1.5.dist-info/LICENSE
BCEmbedding-0.1.5.dist-info/METADATA
BCEmbedding-0.1.5.dist-info/WHEEL
BCEmbedding-0.1.5.dist-info/top_level.txt
BCEmbedding-0.1.5.dist-info/RECORD
