Metadata-Version: 2.1
Name: BCEmbedding
Version: 0.1.5
Summary: A text embedding model and reranking model produced by Netease Youdao Inc., which can be use for dense embedding retrieval and reranking in RAG workflow.
Home-page: https://gitlab.corp.youdao.com/ai/BCEmbedding
Author: Netease Youdao, Inc.
Author-email: shenlei02@corp.netease.com
License: apache-2.0
License-File: LICENSE
Requires-Dist: torch >=1.6.0
Requires-Dist: transformers <4.37.0,>=4.35.0
Requires-Dist: datasets
Requires-Dist: sentence-transformers
